README.txt
setup.cfg
setup.py
fud/__init__.py
fud.advanced_search.egg-info/PKG-INFO
fud.advanced_search.egg-info/SOURCES.txt
fud.advanced_search.egg-info/dependency_links.txt
fud.advanced_search.egg-info/entry_points.txt
fud.advanced_search.egg-info/namespace_packages.txt
fud.advanced_search.egg-info/not-zip-safe
fud.advanced_search.egg-info/paster_plugins.txt
fud.advanced_search.egg-info/requires.txt
fud.advanced_search.egg-info/top_level.txt
fud/advanced_search/__init__.py
fud/advanced_search/setuphandlers.py
fud/advanced_search/tests.py
fud/advanced_search/browser/__init__.py
fud/advanced_search/browser/advancedsearch.py
fud/advanced_search/browser/fudresultview.py